lcode/__init__.py
lcode/__main__.py
lcode/simulation.py
lcode/alt_beam_generator/__init__.py
lcode/alt_beam_generator/beam_generator.py
lcode/alt_beam_generator/beam_segment_shape.py
lcode/alt_beam_generator/beam_shape.py
lcode/alt_beam_generator/eshape.py
lcode/alt_beam_generator/rshape.py
lcode/alt_beam_generator/xishape.py
lcode/beam/__init__.py
lcode/beam/beam_calculate.py
lcode/beam/beam_io.py
lcode/beam/data.py
lcode/beam/profiles.py
lcode/beam/weights.py
lcode/beam3d/__init__.py
lcode/beam3d/beam_calculator.py
lcode/beam3d/beam_io.py
lcode/beam3d/data.py
lcode/beam3d/move.py
lcode/beam3d/weights.py
lcode/beam_generator/__init__.py
lcode/beam_generator/beam_generator.py
lcode/beam_generator/beam_generator2.py
lcode/beam_generator/beam_profiles.py
lcode/config/__init__.py
lcode/config/config.py
lcode/config/default_config.py
lcode/config/default_config_values.py
lcode/config/template.py
lcode/diagnostics/__init__.py
lcode/diagnostics/diagnostics_3d.py
lcode/diagnostics/diagnostics_class.py
lcode/diagnostics/diagnostics_list.py
lcode/diagnostics/particles.py
lcode/diagnostics/process.py
lcode/diagnostics/slice.py
lcode/diagnostics/targets.py
lcode/diagnostics/utils.py
lcode/diagnostics/FXi/FXi.py
lcode/diagnostics/FXi/Strategy.py
lcode/diagnostics/FXi/Strategy3D.py
lcode/diagnostics/FXi/StrategyCircular.py
lcode/diagnostics/FXi/__init__.py
lcode/examples/high-R.py
lcode/examples/original-ssm.py
lcode/mpi/__init__.py
lcode/mpi/beam_io.py
lcode/mpi/transport.py
lcode/mpi/util.py
lcode/plasma/__init__.py
lcode/plasma/data.py
lcode/plasma/fields.py
lcode/plasma/initialization.py
lcode/plasma/move.py
lcode/plasma/ode.py
lcode/plasma/profiles.py
lcode/plasma/rhoj.py
lcode/plasma/solver.py
lcode/plasma3d/__init__.py
lcode/plasma3d/data.py
lcode/plasma3d/fields.py
lcode/plasma3d/initialization.py
lcode/plasma3d/move.py
lcode/plasma3d/noise_filter.py
lcode/plasma3d/profile.py
lcode/plasma3d/rhoj.py
lcode/plasma3d/solver.py
lcode/plasma3d/weights.py
lcode-0.3.1.dist-info/LICENSE
lcode-0.3.1.dist-info/METADATA
lcode-0.3.1.dist-info/WHEEL
lcode-0.3.1.dist-info/top_level.txt
lcode-0.3.1.dist-info/RECORD
