Metadata-Version: 2.1
Name: lcode
Version: 0.3.1
Summary: LCODE is a free software for simulationplasma wakefield acceleration based on QSA.
Home-page: https://lcode.info
Download-URL: https://github.com/lcodePy-team/lcodePy
Author: lcodePy-team
Author-email: team@lcode.info
License: BSD-3-Clause-extended
Keywords: plasma wakefield acceleration,quasistatic approximation,numerical simulation
Classifier: Programming Language :: Python
Classifier: Development Status :: 4 - Beta
Classifier: Intended Audience :: Science/Research
Classifier: Topic :: Scientific/Engineering :: Physics
Classifier: Environment :: Console
Classifier: Operating System :: OS Independent
License-File: LICENSE
Requires-Dist: numba
Requires-Dist: numpy
Requires-Dist: scipy
Requires-Dist: matplotlib
Requires-Dist: mpi4py
